roseApp/__init__.py
roseApp/rose.py
roseApp/cli/compress.py
roseApp/cli/config.py
roseApp/cli/extract.py
roseApp/cli/inspect.py
roseApp/cli/interactive.py
roseApp/cli/list.py
roseApp/cli/load.py
roseApp/config/rose.config.default.yaml
roseApp/config/themes/rose.theme.claude.yaml
roseApp/config/themes/rose.theme.gruvbox.yaml
roseApp/config/themes/rose.theme.nord.yaml
roseApp/config/themes/rose.theme.solarized.yaml
roseApp/core/__init__.py
roseApp/core/cache.py
roseApp/core/config.py
roseApp/core/errors.py
roseApp/core/events.py
roseApp/core/logging.py
roseApp/core/model.py
roseApp/core/output.py
roseApp/core/parser.py
roseApp/core/pipeline.py
roseApp/core/writer.py
roseApp/docs/api_reference.md
roseApp/docs/architecture.md
roseApp/docs/command_orchestration.md
roseApp/docs/configuration.md
roseApp/docs/design.md
roseApp/docs/headless_sdk_architecture.md
roseApp/docs/theming.md
roseApp/tui/__init__.py
roseApp/tui/config_app.py
roseApp/tui/dialogs.py
roseApp/tui/inspect_app.py
roseApp/tui/interactive_comp.tcss
roseApp/tui/list_app.py
roseApp/tui/main_app.py
roseApp/tui/styles.tcss
roseApp/tui/theme.py
roseApp/tui/manual/inspect_help.md
roseApp/tui/widgets/__init__.py
roseApp/tui/widgets/hint.py
roseApp/tui/widgets/multi_question.py
roseApp/tui/widgets/path_search.py
roseApp/tui/widgets/question.py
rose_bag-0.9.7.dist-info/METADATA
rose_bag-0.9.7.dist-info/WHEEL
rose_bag-0.9.7.dist-info/entry_points.txt
rose_bag-0.9.7.dist-info/licenses/LICENSE
rose_bag-0.9.7.dist-info/RECORD
