Metadata-Version: 2.4
Name: rose-bag
Version: 0.9.7
Summary: A modern CLI/TUI tool for ROS bag file analysis and filtering
Project-URL: Homepage, https://github.com/hanxiaomax/rose
Project-URL: Bug Tracker, https://github.com/hanxiaomax/rose/issues
Author-email: Lingfeng_ai <hanxiaomax@qq.com>
License: MIT License
License-File: LICENSE
Keywords: bag,cli,filter,robotics,ros,tui,visualization
Classifier: Development Status :: 4 - Beta
Classifier: Environment :: Console
Classifier: Intended Audience :: Developers
Classifier: Intended Audience :: Science/Research
Classifier: License :: OSI Approved :: MIT License
Classifier: Operating System :: OS Independent
Classifier: Programming Language :: Python :: 3
Classifier: Programming Language :: Python :: 3.8
Classifier: Programming Language :: Python :: 3.9
Classifier: Programming Language :: Python :: 3.10
Classifier: Programming Language :: Python :: 3.11
Classifier: Topic :: Scientific/Engineering :: Visualization
Classifier: Topic :: Software Development :: Libraries :: Python Modules
Requires-Python: >=3.8
Requires-Dist: click>=8.0.0
Requires-Dist: lz4>=4.3.0
Requires-Dist: pandas>=1.3.0
Requires-Dist: plotext>=5.2.0
Requires-Dist: pydantic-settings
Requires-Dist: pydantic>=2.0.0
Requires-Dist: pyyaml>=6.0
Requires-Dist: rich>=13.0.0
Requires-Dist: rosbags>=0.9.16
Requires-Dist: textual-plotext>=0.2.0
Requires-Dist: textual>=0.40.0
Requires-Dist: typer>=0.9.0
